sdk/__init__.py
sdk/api_client.py
sdk/image_generation.py
tests/__init__.py
tests/test_image_generation.py
InstantLight-1.2.0.dist-info/LICENSE
InstantLight-1.2.0.dist-info/METADATA
InstantLight-1.2.0.dist-info/WHEEL
InstantLight-1.2.0.dist-info/top_level.txt
InstantLight-1.2.0.dist-info/RECORD
