Metadata-Version: 2.1
Name: InstantLight
Version: 1.2.0
Summary: Python SDK for InstantLight
Home-page: https://github.com/FotographerAI/InstantLight-sdk/
Author: Saliou Kane
Author-email: saliou@fotographer.ai
Classifier: Programming Language :: Python :: 3
Classifier: License :: OSI Approved :: MIT License
Classifier: Operating System :: OS Independent
Requires-Python: >=3.6
License-File: LICENSE
Requires-Dist: requests
